aioflux/__init__.py
aioflux/flux.py
aioflux/core/__init__.py
aioflux/core/metrics.py
aioflux/core/storage/__init__.py
aioflux/core/storage/base.py
aioflux/core/storage/hybrid.py
aioflux/core/storage/memory.py
aioflux/core/storage/redis_.py
aioflux/decorators/__init__.py
aioflux/decorators/circuit_breaker.py
aioflux/decorators/queue.py
aioflux/decorators/rate_limit.py
aioflux/limiters/__init__.py
aioflux/limiters/adaptive.py
aioflux/limiters/base.py
aioflux/limiters/composite.py
aioflux/limiters/leaky_bucket.py
aioflux/limiters/sliding_window.py
aioflux/limiters/token_bucket.py
aioflux/managers/__init__.py
aioflux/managers/coordinator.py
aioflux/managers/pool.py
aioflux/managers/scheduler.py
aioflux/queues/__init__.py
aioflux/queues/broadcast.py
aioflux/queues/dedupe.py
aioflux/queues/delay.py
aioflux/queues/fifo.py
aioflux/queues/priority.py
aioflux/queues/base/__init__.py
aioflux/queues/base/base.py
aioflux/queues/base/typed_queue.py
aioflux/utils/__init__.py
aioflux/utils/backoff.py
aioflux/utils/batch.py
aioflux/utils/common.py
aioflux/utils/monitoring.py
aioflux-0.1.5.dist-info/licenses/LICENSE
aioflux-0.1.5.dist-info/METADATA
aioflux-0.1.5.dist-info/WHEEL
aioflux-0.1.5.dist-info/top_level.txt
aioflux-0.1.5.dist-info/RECORD
