Metadata-Version: 2.4
Name: aioflux
Version: 0.1.5
Summary: High-performance async rate limiting and queue management
Home-page: https://github.com/Asmin963/aioflux
Author: zlexdev
License: MIT
Project-URL: Homepage, https://github.com/Asmin963/aioflux
Project-URL: Documentation, https://aioflux.readthedocs.io
Project-URL: Repository, https://github.com/Asmin963/aioflux
Project-URL: Issues, https://github.com/Asmin963/aioflux/issues
Classifier: Development Status :: 4 - Beta
Classifier: Intended Audience :: Developers
Classifier: License :: OSI Approved :: MIT License
Classifier: Programming Language :: Python :: 3
Classifier: Programming Language :: Python :: 3.8
Classifier: Programming Language :: Python :: 3.9
Classifier: Programming Language :: Python :: 3.10
Classifier: Programming Language :: Python :: 3.11
Classifier: Topic :: Software Development :: Libraries :: Python Modules
Requires-Python: >=3.8
License-File: LICENSE
Requires-Dist: redis>=2.0.0
Requires-Dist: aiohttp>=3.8.0
Provides-Extra: dev
Requires-Dist: pytest>=7.0.0; extra == "dev"
Requires-Dist: pytest-asyncio>=0.20.0; extra == "dev"
Requires-Dist: pytest-cov>=4.0.0; extra == "dev"
Requires-Dist: black>=22.0.0; extra == "dev"
Requires-Dist: flake8>=6.0.0; extra == "dev"
Requires-Dist: isort>=5.12.0; extra == "dev"
Requires-Dist: pre-commit>=3.0.0; extra == "dev"
Dynamic: license-file
Dynamic: requires-python
